{
  "id": "cms-enforcement-tracker-3bcf366e9be2ccbf",
  "title": "ITALY enforcement action against S.M. Trattamento Acqua di XX (30,000)",
  "source": "CMS Enforcement Tracker",
  "sourceId": "cms-enforcement-tracker",
  "sourceUrl": "https://www.enforcementtracker.com/",
  "publishedDate": "2026-02-26",
  "decisionDate": "2026-02-26",
  "authorityPublicationDate": null,
  "platformPublicationDate": null,
  "summary": "Insufficient legal basis for data processing The Italian DPA has imposed a fine of EUR 30,000 on S.M. Trattamento Acqua di XY. The controller had been active in direct marketing, using automated calls for this purpose. However, the controller failed to base the data processing on an adequate legal basis and failed to implement appropriate...",
  "category": "decisions",
  "dedupKey": "italy enforcement action against s m trattamento acqua di xx 30 000|2026-02-26",
  "tags": [
    "enforcement",
    "fines",
    "italy",
    "industry-and-commerce",
    "etid-3125"
  ],
  "originalLink": "https://www.garanteprivacy.it/web/guest/home/docweb/-/docweb-display/docweb/10236228",
  "fetchedAt": "2026-04-30T19:06:09.541Z"
}
