{
  "id": "gdprhub-recentchanges-da75cbd15a8ed35f",
  "title": "Persónuvernd (Island) - 2025020471",
  "source": "GDPRhub",
  "sourceId": "gdprhub-recentchanges",
  "sourceUrl": "https://gdprhub.eu/",
  "publishedDate": "2026-05-29",
  "decisionDate": null,
  "authorityPublicationDate": null,
  "platformPublicationDate": "2026-05-29",
  "summary": "New GDPRhub DPA decision added for Persónuvernd (Island) - 2025020471. Jurisdiction: Iceland. Original source listed by GDPRhub: Persónuvernd.",
  "category": "decisions",
  "dedupKey": "personuvernd island 2025020471|2026-05-29",
  "tags": [
    "gdprhub",
    "case-law",
    "island"
  ],
  "originalLink": "https://gdprhub.eu/index.php?title=Pers%C3%B3nuvernd%20(Island)%20-%202025020471",
  "fetchedAt": "2026-05-29T20:08:28.413Z"
}
