{
  "id": "gdprhub-recentchanges-4cb4b59dd76ef6dd",
  "title": "Persónuvernd (Island) - 2022040716",
  "source": "GDPRhub",
  "sourceId": "gdprhub-recentchanges",
  "sourceUrl": "https://gdprhub.eu/",
  "publishedDate": "2026-05-29",
  "decisionDate": null,
  "authorityPublicationDate": null,
  "platformPublicationDate": "2026-05-29",
  "summary": "GDPRhub updated its case-law record for Persónuvernd (Island) - 2022040716.",
  "category": "decisions",
  "dedupKey": "personuvernd island 2022040716|2026-05-29",
  "tags": [
    "gdprhub",
    "case-law",
    "island"
  ],
  "originalLink": "https://gdprhub.eu/index.php?title=Pers%C3%B3nuvernd%20(Island)%20-%202022040716",
  "fetchedAt": "2026-06-01T02:43:33.282Z"
}
