{
  "id": "gdprhub-recentchanges-9189700126d0f4c7",
  "title": "DSB (Austria) - 2025-0.923.556",
  "source": "GDPRhub",
  "sourceId": "gdprhub-recentchanges",
  "sourceUrl": "https://gdprhub.eu/",
  "publishedDate": "2026-04-30",
  "decisionDate": null,
  "authorityPublicationDate": null,
  "platformPublicationDate": "2026-04-30",
  "summary": "New GDPRhub DPA decision added for DSB (Austria) - 2025-0.923.556. Jurisdiction: Austria. Original source listed by GDPRhub: RIS.",
  "category": "decisions",
  "dedupKey": "dsb austria 2025 0 923 556|2026-04-30",
  "tags": [
    "gdprhub",
    "case-law",
    "austria"
  ],
  "originalLink": "https://gdprhub.eu/index.php?title=DSB%20(Austria)%20-%202025-0.923.556",
  "fetchedAt": "2026-05-01T12:56:45.604Z"
}
