{
  "id": "opc-canada-pipeda-investigations-be582bb4612b30bd",
  "title": "Compliance agreement between the Privacy Commissioner of Canada and the World Anti-Doping Agency",
  "source": "Canada OPC Business Investigations",
  "sourceId": "opc-canada-pipeda-investigations",
  "sourceUrl": "https://www.priv.gc.ca/en/opc-actions-and-decisions/investigations/investigations-into-businesses/",
  "publishedDate": "2026-03-17",
  "decisionDate": "2026-03-17",
  "authorityPublicationDate": "2026-03-17",
  "platformPublicationDate": "2026-03-17",
  "summary": "WHEREAS the Privacy Commissioner of Canada (the Commissioner) is responsible for the administration and enforcement of Part 1 of the Personal Information Protection and Electronic Documents Act , S.C. 2000, c. 5 (the Act), which governs the collection, use or disclosure of personal information by the World Anti-Doping Agency (WADA) in the...",
  "category": "decisions",
  "dedupKey": "compliance agreement between the privacy commissioner of canada and the world anti doping agency|2026-03-17",
  "tags": [
    "canada",
    "opc",
    "pipeda",
    "investigations",
    "compliance-agreement",
    "enforcement"
  ],
  "sourceDetailUrl": "https://www.priv.gc.ca/en/opc-actions-and-decisions/investigations/investigations-into-businesses/2026/2026-wada-ca/",
  "documentUrl": null,
  "localDocumentUrl": null,
  "documentContentType": null,
  "documentSizeBytes": null,
  "documentSha256": null,
  "documentDownloadedAt": null,
  "documentDownloadError": null,
  "originalLink": "https://www.priv.gc.ca/en/opc-actions-and-decisions/investigations/investigations-into-businesses/2026/2026-wada-ca/",
  "fetchedAt": "2026-06-10T20:08:43.678Z"
}
