{
  "id": "opc-canada-pipeda-investigations-a49ddce1b6724bcb",
  "title": "Supplementary identification required to obtain members? discount",
  "source": "Canada OPC Business Investigations",
  "sourceId": "opc-canada-pipeda-investigations",
  "sourceUrl": "https://www.priv.gc.ca/en/opc-actions-and-decisions/investigations/investigations-into-businesses/",
  "publishedDate": "2006-09-07",
  "decisionDate": "2005-12-16",
  "authorityPublicationDate": "2005-12-16",
  "platformPublicationDate": "2006-09-07",
  "summary": "A member of a not-for-profit association complained that he was required to show a second piece of identification, in addition to his membership card, when purchasing goods or services from the association. He thought that his membership card should be sufficient identification and that the collection of further personal information was u...",
  "category": "decisions",
  "dedupKey": "supplementary identification required to obtain members discount|2005-12-16",
  "tags": [
    "canada",
    "opc",
    "pipeda",
    "investigations",
    "settled-case-summary-17",
    "settled"
  ],
  "sourceDetailUrl": "https://www.priv.gc.ca/en/opc-actions-and-decisions/investigations/investigations-into-businesses/ser/2005/s17_051216/",
  "documentUrl": null,
  "localDocumentUrl": null,
  "documentContentType": null,
  "documentSizeBytes": null,
  "documentSha256": null,
  "documentDownloadedAt": null,
  "documentDownloadError": null,
  "originalLink": "https://www.priv.gc.ca/en/opc-actions-and-decisions/investigations/investigations-into-businesses/ser/2005/s17_051216/",
  "fetchedAt": "2026-06-10T20:08:43.678Z"
}
