{
  "id": "opc-canada-pipeda-investigations-489e8b0b49d4042c",
  "title": "Customer gets signed up for retailer credit card without his consent",
  "source": "Canada OPC Business Investigations",
  "sourceId": "opc-canada-pipeda-investigations",
  "sourceUrl": "https://www.priv.gc.ca/en/opc-actions-and-decisions/investigations/investigations-into-businesses/",
  "publishedDate": "2017-03-15",
  "decisionDate": "2016-03-31",
  "authorityPublicationDate": "2016-03-31",
  "platformPublicationDate": "2017-03-15",
  "summary": "While shopping in a retail store, an individual was approached by a salesperson and asked to join a loyalty program. He agreed to join the loyalty program, and provided the salesperson with his driver’s licence to complete the registration. The individual was surprised to receive a credit card from the bank associated with the retailer a...",
  "category": "decisions",
  "dedupKey": "customer gets signed up for retailer credit card without his consent|2016-03-31",
  "tags": [
    "canada",
    "opc",
    "pipeda",
    "investigations",
    "pipeda-case-summary-2016-012"
  ],
  "sourceDetailUrl": "https://www.priv.gc.ca/en/opc-actions-and-decisions/investigations/investigations-into-businesses/2016/pipeda-2016-012/",
  "documentUrl": null,
  "localDocumentUrl": null,
  "documentContentType": null,
  "documentSizeBytes": null,
  "documentSha256": null,
  "documentDownloadedAt": null,
  "documentDownloadError": null,
  "originalLink": "https://www.priv.gc.ca/en/opc-actions-and-decisions/investigations/investigations-into-businesses/2016/pipeda-2016-012/",
  "fetchedAt": "2026-06-10T20:08:43.678Z"
}
