{
  "id": "pdpc-commissions-decisions-c2f3b0975f9282a5",
  "title": "Breach of the Protection Obligation by Cortina Watch",
  "source": "Singapore PDPC Decisions",
  "sourceId": "pdpc-commissions-decisions",
  "sourceUrl": "https://www.pdpc.gov.sg/all-commissions-decisions",
  "publishedDate": "2024-05-23",
  "decisionDate": "2024-05-23",
  "authorityPublicationDate": "2024-05-23",
  "platformPublicationDate": "2024-05-23",
  "summary": "Directions were issued to Cortina Watch for failing to put in place reasonable security arrangements to protect individuals' personal data in its possession or under its control.",
  "category": "decisions",
  "dedupKey": "breach of the protection obligation by cortina watch|2024-05-23",
  "tags": [
    "singapore",
    "pdpc",
    "enforcement",
    "protection",
    "directions"
  ],
  "sourceDetailUrl": "https://www.pdpc.gov.sg/all-commissions-decisions/2024/05/breach-of-the-protection-obligation-by-cortina-watch",
  "documentUrl": "https://www.pdpc.gov.sg/-/media/files/pdpc/pdf-files/commissions-decisions/gd_cortina-watch-pte-ltd_280324.pdf",
  "localDocumentUrl": "/decision-documents/official-decisions/pdpc-commissions-decisions/pdpc-commissions-decisions-c2f3b0975f9282a5.pdf",
  "documentContentType": "application/pdf",
  "documentSizeBytes": 191604,
  "documentSha256": "1d756acbe26ffac2baff58da2866d097d7e49b9b0a6613141a6eda6df8d7349b",
  "documentDownloadedAt": "2026-04-05T15:03:07.470Z",
  "documentDownloadError": null,
  "originalLink": "https://www.pdpc.gov.sg/-/media/files/pdpc/pdf-files/commissions-decisions/gd_cortina-watch-pte-ltd_280324.pdf",
  "fetchedAt": "2026-04-16T04:11:05.443Z"
}
